{
	"mainList":[
			{
			"id":"1001",
			"src1":"img/huishi-1.jpg",
			"p":"慧氏启赋幼儿配方奶粉三阶段（12-36月）900g（新配方）",
			"link":"#",
			"a":"加9.9元换购",
			"span":"￥298.00",
			"link1":"#",
			"a1":"立即抢购",
			"i":"&#xe649"
			},{
			"id":"1002",
			"src1":"img/huishi-2.jpg",
			"p":"慧氏启赋幼儿配方奶粉三阶段（12-36月）900g（新配方）",
			"link":"#",
			"a":"加9.9元换购",
			"span":"￥98.00",
			"link1":"#",
			"a1":"立即抢购",
			"i":"&#xe649"
			},{
			"id":"1003",
			"src1":"img/huishi-3.jpg",
			"p":"慧氏启赋幼儿配方奶粉三阶段（12-36月）900g（新配方）",
			"link":"#",
			"a":"加9.9元换购",
			"span":"￥28.00",
			"link1":"#",
			"a1":"立即抢购",
			"i":"&#xe649"
			},{
			"id":"1004",
			"src1":"img/huishi-8.jpg",
			"p":"慧氏启赋幼儿配方奶粉三阶段（12-36月）900g（新配方）",
			"link":"#",
			"a":"加9.9元换购",
			"span":"￥58.00",
			"link1":"#",
			"a1":"立即抢购",
			"i":"&#xe649"
			},{
			"id":"1005",
			"src1":"img/huishi-5.jpg",
			"p":"慧氏启赋幼儿配方奶粉三阶段（12-36月）900g（新配方）",
			"link":"#",
			"a":"加9.9元换购",
			"span":"￥88.00",
			"link1":"#",
			"a1":"立即抢购",
			"i":"&#xe649"
			},{
			"id":"1006",
			"src1":"img/huishi-6.jpg",
			"p":"慧氏启赋幼儿配方奶粉三阶段（12-36月）900g（新配方）",
			"link":"#",
			"a":"加9.9元换购",
			"span":"￥98.00",
			"link1":"#",
			"a1":"立即抢购",
			"i":"&#xe649"
			},{
			"id":"1007",
			"src1":"img/huishi-7.jpg",
			"p":"慧氏启赋幼儿配方奶粉三阶段（12-36月）900g（新配方）",
			"link":"#",
			"a":"加9.9元换购",
			"span":"￥298.00",
			"link1":"#",
			"a1":"立即抢购",
			"i":"&#xe649"
			},{
			"id":"1019",
			"src1":"img/huishi-6.jpg",
			"p":"慧氏启赋幼儿配方奶粉三阶段（12-36月）900g（新配方）",
			"link":"#",
			"a":"加9.9元换购",
			"span":"￥98.00",
			"link1":"#",
			"a1":"立即抢购",
			"i":"&#xe649"
			},{
			"id":"1020",
			"src1":"img/huishi-7.jpg",
			"p":"慧氏启赋幼儿配方奶粉三阶段（12-36月）900g（新配方）",
			"link":"#",
			"a":"加9.9元换购",
			"span":"￥298.00",
			"link1":"#",
			"a1":"立即抢购",
			"i":"&#xe649"
			}
		],
		"mainList1":[
			{
			"id":"1008",
			"src1":"img/huishi-9.jpg",
			"p":"慧氏启赋幼儿配方奶粉三阶段（12-36月）900g（新配方）",
			"link":"#",
			"a":"加9.9元换购",
			"span":"￥298.00",
			"link1":"#",
			"a1":"立即抢购",
			"i":"&#xe649"
			},{
			"id":"1009",
			"src1":"img/huishi-10.jpg",
			"p":"慧氏启赋幼儿配方奶粉三阶段（12-36月）900g（新配方）",
			"link":"#",
			"a":"加9.9元换购",
			"span":"￥298.00",
			"link1":"#",
			"a1":"立即抢购",
			"i":"&#xe649"
			},{
			"id":"10010",
			"src1":"img/huishi-11.jpg",
			"p":"慧氏启赋幼儿配方奶粉三阶段（12-36月）900g（新配方）",
			"link":"#",
			"a":"加9.9元换购",
			"span":"￥298.00",
			"link1":"#",
			"a1":"立即抢购",
			"i":"&#xe649"
			},{
			"id":"1011",
			"src1":"img/huishi-12.jpg",
			"p":"慧氏启赋幼儿配方奶粉三阶段（12-36月）900g（新配方）",
			"link":"#",
			"a":"加9.9元换购",
			"span":"￥298.00",
			"link1":"#",
			"a1":"立即抢购",
			"i":"&#xe649"
			},{
			"id":"1012",
			"src1":"img/huishi-13.jpg",
			"p":"慧氏启赋幼儿配方奶粉三阶段（12-36月）900g（新配方）",
			"link":"#",
			"a":"加9.9元换购",
			"span":"￥298.00",
			"link1":"#",
			"a1":"立即抢购",
			"i":"&#xe649"
			},{
			"id":"1013",
			"src1":"img/huishi-14.jpg",
			"p":"慧氏启赋幼儿配方奶粉三阶段（12-36月）900g（新配方）",
			"link":"#",
			"a":"加9.9元换购",
			"span":"￥298.00",
			"link1":"#",
			"a1":"立即抢购",
			"i":"&#xe649"
			},{
			"id":"1014",
			"src1":"img/huishi-15.jpg",
			"p":"慧氏启赋幼儿配方奶粉三阶段（12-36月）900g（新配方）",
			"link":"#",
			"a":"加9.9元换购",
			"span":"￥56.00",
			"link1":"#",
			"a1":"立即抢购",
			"i":"&#xe649"
			},{
			"id":"1015",
			"src1":"img/huishi-13.jpg",
			"p":"慧氏启赋幼儿配方奶粉三阶段（12-36月）900g（新配方）",
			"link":"#",
			"a":"加9.9元换购",
			"span":"￥98.00",
			"link1":"#",
			"a1":"立即抢购",
			"i":"&#xe649"
			},{
			"id":"1016",
			"src1":"img/huishi-14.jpg",
			"p":"慧氏启赋幼儿配方奶粉三阶段（12-36月）900g（新配方）",
			"link":"#",
			"a":"加9.9元换购",
			"span":"￥28.00",
			"link1":"#",
			"a1":"立即抢购",
			"i":"&#xe649"
			},{
			"id":"1017",
			"src1":"img/huishi-15.jpg",
			"p":"慧氏启赋幼儿配方奶粉三阶段（12-36月）900g（新配方）",
			"link":"#",
			"a":"加9.9元换购",
			"span":"￥198.00",
			"link1":"#",
			"a1":"立即抢购",
			"i":"&#xe649"
			}
		]
}

